{
  "collapse-filter": true,
  "search": "",
  "showTags": false,
  "showAttachments": false,
  "hideUnresolved": false,
  "showOrphans": true,
  "collapse-color-groups": false,
  "colorGroups": [
    {
      "query": "path:\"00.Index\"",
      "color": {
        "a": 1,
        "rgb": 15254855
      }
    },
    {
      "query": "path:\"01_Core_Design\"",
      "color": {
        "a": 1,
        "rgb": 15158332
      }
    },
    {
      "query": "path:\"02_System_Architecture\"",
      "color": {
        "a": 1,
        "rgb": 1752220
      }
    },
    {
      "query": "path:\"04_Data_Model\"",
      "color": {
        "a": 1,
        "rgb": 10181046
      }
    },
    {
      "query": "path:\"Work_Log\"",
      "color": {
        "a": 1,
        "rgb": 15105570
      }
    }
  ],
  "collapse-display": false,
  "showArrow": false,
  "textFadeMultiplier": 0,
  "nodeSizeMultiplier": 1,
  "lineSizeMultiplier": 1,
  "collapse-forces": false,
  "centerStrength": 0.518713248970312,
  "repelStrength": 10,
  "linkStrength": 1,
  "linkDistance": 250,
  "scale": 0.7132754626224413,
  "close": true
}